setup.py
reverseip/__init__.py
reverseip.egg-info/PKG-INFO
reverseip.egg-info/SOURCES.txt
reverseip.egg-info/dependency_links.txt
reverseip.egg-info/entry_points.txt
reverseip.egg-info/not-zip-safe
reverseip.egg-info/requires.txt
reverseip.egg-info/top_level.txt